build/lib/pyproxy/__init__.py
build/lib/pyproxy/__main__.py
build/lib/pyproxy/pyproxy.py
build/lib/pyproxy/server.py
build/lib/pyproxy/handlers/__init__.py
build/lib/pyproxy/handlers/client.py
build/lib/pyproxy/handlers/http.py
build/lib/pyproxy/handlers/https.py
build/lib/pyproxy/modules/__init__.py
build/lib/pyproxy/modules/cancel_inspect.py
build/lib/pyproxy/modules/custom_header.py
build/lib/pyproxy/modules/filter.py
build/lib/pyproxy/modules/shortcuts.py
build/lib/pyproxy/monitoring/__init__.py
build/lib/pyproxy/monitoring/auth.py
build/lib/pyproxy/monitoring/monitor.py
build/lib/pyproxy/monitoring/routes.py
build/lib/pyproxy/utils/__init__.py
build/lib/pyproxy/utils/args.py
build/lib/pyproxy/utils/config.py
build/lib/pyproxy/utils/crypto.py
build/lib/pyproxy/utils/http_req.py
build/lib/pyproxy/utils/logger.py
build/lib/tests/modules/__init__.py
build/lib/tests/modules/test_cancel_inspect.py
build/lib/tests/modules/test_custom_header.py
build/lib/tests/modules/test_filter.py
build/lib/tests/modules/test_shortcuts.py
build/lib/tests/utils/__init__.py
build/lib/tests/utils/test_crypto.py
build/lib/tests/utils/test_http_req.py
build/lib/tests/utils/test_logger.py
pyproxy/__init__.py
pyproxy/__main__.py
pyproxy/pyproxy.py
pyproxy/server.py
pyproxy/handlers/__init__.py
pyproxy/handlers/client.py
pyproxy/handlers/http.py
pyproxy/handlers/https.py
pyproxy/modules/__init__.py
pyproxy/modules/cancel_inspect.py
pyproxy/modules/custom_header.py
pyproxy/modules/filter.py
pyproxy/modules/shortcuts.py
pyproxy/monitoring/__init__.py
pyproxy/monitoring/auth.py
pyproxy/monitoring/messages.pot
pyproxy/monitoring/monitor.py
pyproxy/monitoring/routes.py
pyproxy/monitoring/translations/en/LC_MESSAGES/messages.mo
pyproxy/monitoring/translations/en/LC_MESSAGES/messages.po
pyproxy/monitoring/translations/fr/LC_MESSAGES/messages.mo
pyproxy/monitoring/translations/fr/LC_MESSAGES/messages.po
pyproxy/utils/__init__.py
pyproxy/utils/args.py
pyproxy/utils/config.py
pyproxy/utils/crypto.py
pyproxytools-0.5.1.dist-info/licenses/LICENSE
pyproxytools-0.5.1.dist-info/METADATA
pyproxytools-0.5.1.dist-info/WHEEL
pyproxytools-0.5.1.dist-info/entry_points.txt
pyproxytools-0.5.1.dist-info/top_level.txt
pyproxytools-0.5.1.dist-info/RECORD
