Metadata-Version: 2.4
Name: pyproxytools
Version: 0.5.1
Summary: Lightweight and fast python web proxy
Author: pyproxytools
License-Expression: MIT
Project-URL: Documentation, https://pyproxytools.github.io/pyproxy-docs/
Project-URL: Issue tracker, https://github.com/pyproxytools/pyproxy/issues
Classifier: Development Status :: 5 - Production/Stable
Classifier: Intended Audience :: Developers
Classifier: Natural Language :: English
Classifier: Operating System :: OS Independent
Classifier: Programming Language :: Python :: 3.8
Classifier: Programming Language :: Python :: 3.9
Classifier: Programming Language :: Python :: 3.10
Classifier: Programming Language :: Python :: 3.11
Classifier: Programming Language :: Python :: 3.12
Classifier: Programming Language :: Python :: 3.13
Classifier: Topic :: Internet
Classifier: Topic :: Software Development :: Libraries
Classifier: Topic :: Software Development :: Libraries :: Python Modules
Classifier: Topic :: Utilities
Classifier: Typing :: Typed
License-File: LICENSE
Requires-Dist: rich-argparse>=1.7.1
Requires-Dist: pyOpenSSL>=25.3.0
Requires-Dist: requests>=2.32.5
Requires-Dist: Flask>=3.1.2
Requires-Dist: Flask-HTTPAuth>=4.8.0
Requires-Dist: Flask-Babel>=4.0.0
Requires-Dist: psutil>=7.1.0
Requires-Dist: colorlog>=6.9.0
Dynamic: license-file
